openobd/__init__.py
openobd/_metadata.py
openobd/communication/__init__.py
openobd/communication/connection_monitor.py
openobd/communication/doip_socket.py
openobd/communication/isotp_socket.py
openobd/communication/kline_socket.py
openobd/communication/raw_socket.py
openobd/communication/response_exceptions.py
openobd/communication/terminal15_socket.py
openobd/communication/tp20_socket.py
openobd/communication/uds_request_handler.py
openobd/core/__init__.py
openobd/core/_token.py
openobd/core/exceptions.py
openobd/core/function_broker.py
openobd/core/grpc_factory.py
openobd/core/openobd.py
openobd/core/session.py
openobd/core/session_controller.py
openobd/core/session_token_handler.py
openobd/core/stream_handler.py
openobd/core/utils.py
openobd/functions/__init__.py
openobd/functions/function_context_handler.py
openobd/functions/function_exceptions.py
openobd/ui/__init__.py
openobd/ui/ui_handler.py
openobd-1.25.2.dist-info/licenses/LICENSE
openobd-1.25.2.dist-info/METADATA
openobd-1.25.2.dist-info/WHEEL
openobd-1.25.2.dist-info/top_level.txt
openobd-1.25.2.dist-info/RECORD
