Metadata-Version: 2.4
Name: openobd
Version: 1.25.2
Summary: Jifeline Networks openOBD Python Client Library
Author-email: Gerhard de Koning Gans <gerhard@factorit.nl>, Wessel van Tunen <wessel@factorit.nl>, Rohaan Ghosh <rohaan@factorit.nl>, Sander de Mooij <sanderdemooij@factorit.nl>
Maintainer-email: Gerhard de Koning Gans <gerhard@factorit.nl>, Wessel van Tunen <wessel@factorit.nl>, Rohaan Ghosh <rohaan@factorit.nl>, Sander de Mooij <sanderdemooij@factorit.nl>, Robert Horlings <robert.horlings@factorit.nl>
Project-URL: Homepage, https://www.openobd.com
Keywords: openOBD,Protocol,gRPC,Jifeline,Remote,Diagnostics,OBD,On-board,Automotive,Car,Vehicle,CAN,K-line,DoIP
Platform: any
Classifier: Development Status :: 4 - Beta
Classifier: License :: OSI Approved :: MIT License
Classifier: Operating System :: OS Independent
Classifier: Programming Language :: Python :: 3
Classifier: Topic :: Communications
Requires-Python: >=3.11
License-File: LICENSE
Requires-Dist: openobd-protocol==1.25.0
Dynamic: license-file
